logger_36/__init__.py
logger_36/version.py
logger_36/api/chronos.py
logger_36/api/logger.py
logger_36/api/memory.py
logger_36/api/message.py
logger_36/api/storage.py
logger_36/catalog/config/console_rich.py
logger_36/catalog/config/optional.py
logger_36/catalog/handler/console.py
logger_36/catalog/handler/console_rich.py
logger_36/catalog/handler/file.py
logger_36/catalog/handler/generic.py
logger_36/catalog/handler/memory.py
logger_36/catalog/logger/chronos.py
logger_36/catalog/logger/gpu.py
logger_36/catalog/logger/memory.py
logger_36/catalog/logger/system.py
logger_36/config/issue.py
logger_36/config/memory.py
logger_36/config/message.py
logger_36/config/rule.py
logger_36/config/system.py
logger_36/constant/chronos.py
logger_36/constant/error.py
logger_36/constant/html.py
logger_36/constant/issue.py
logger_36/constant/logger.py
logger_36/constant/memory.py
logger_36/constant/message.py
logger_36/constant/path.py
logger_36/constant/record.py
logger_36/constant/rule.py
logger_36/constant/system.py
logger_36/extension/file.py
logger_36/extension/inspection.py
logger_36/extension/line.py
logger_36/extension/sentinel.py
logger_36/instance/logger.py
logger_36/instance/loggers.py
logger_36/task/storage.py
logger_36/task/format/memory.py
logger_36/task/format/message.py
logger_36/task/measure/chronos.py
logger_36/task/measure/memory.py
logger_36/type/handler.py
logger_36/type/issue.py
logger_36/type/logger.py
logger_36/type/loggers.py
logger_36-2025.29.dist-info/METADATA
logger_36-2025.29.dist-info/WHEEL
logger_36-2025.29.dist-info/top_level.txt
logger_36-2025.29.dist-info/RECORD
