Metadata-Version: 2.4
Name: logger-36
Version: 2025.29
Summary: Simple logger with a catalog of handlers
Home-page: https://src.koda.cnrs.fr/eric.debreuve/logger-36/
Author: Eric Debreuve
Author-email: eric.debreuve@cnrs.fr
License: CeCILL-2.1
Project-URL: Documentation, https://src.koda.cnrs.fr/eric.debreuve/logger-36/-/wikis/home
Project-URL: Source, https://src.koda.cnrs.fr/eric.debreuve/logger-36/
Keywords: log,warning,error
Classifier: Topic :: Software Development
Classifier: Intended Audience :: Developers
Classifier: License :: OSI Approved :: CEA CNRS Inria Logiciel Libre License, version 2.1 (CeCILL-2.1)
Classifier: Programming Language :: Python :: 3
Classifier: Development Status :: 5 - Production/Stable
Requires-Python: >=3.11
Dynamic: author
Dynamic: author-email
Dynamic: classifier
Dynamic: description
Dynamic: description-content-type
Dynamic: home-page
Dynamic: keywords
Dynamic: license
Dynamic: project-url
Dynamic: requires-python
Dynamic: summary
